[
    {
        "class_id": 5,
        "x": 123,
        "y": 398,
        "width": 404.5,
        "height": 159.5
    },
    {
        "class_id": 5,
        "x": 166,
        "y": 351,
        "width": 346.5,
        "height": 117
    },
    {
        "class_id": 5,
        "x": 88,
        "y": 270,
        "width": 349.5,
        "height": 139.5
    },
    {
        "class_id": 5,
        "x": 120,
        "y": 44,
        "width": 184.5,
        "height": 116.5
    },
    {
        "class_id": 5,
        "x": 61,
        "y": 231,
        "width": 312.5,
        "height": 120.5
    },
    {
        "class_id": 5,
        "x": 13,
        "y": 109,
        "width": 185,
        "height": 144.5
    },
    {
        "class_id": 5,
        "x": 114,
        "y": 85,
        "width": 247.5,
        "height": 139
    },
    {
        "class_id": 5,
        "x": 169,
        "y": 213,
        "width": 227,
        "height": 111
    }
]